subquery/.DS_Store
subquery/__init__.py
subquery/core.py
subquery/ollama_model.py
subquery/transformers_model.py
subquery-0.1.2.dist-info/METADATA
subquery-0.1.2.dist-info/WHEEL
subquery-0.1.2.dist-info/RECORD
