Metadata-Version: 2.1
Name: subquery
Version: 0.1.2
Summary: A package to generate subqueries and follow-up questions
License: MIT
Author: andthattoo
Author-email: omer@firstbatch.xyz
Requires-Python: >=3.9,<4.0
Classifier: License :: OSI Approved :: MIT License
Classifier: Programming Language :: Python :: 3
Classifier: Programming Language :: Python :: 3.9
Classifier: Programming Language :: Python :: 3.10
Classifier: Programming Language :: Python :: 3.11
Classifier: Programming Language :: Python :: 3.12
Requires-Dist: ollama (>=0.3.1,<0.4.0)
Requires-Dist: torch (>=2.4.0,<3.0.0)
Requires-Dist: transformers (>=4.44.0,<5.0.0)
